<?xml version='1.0' encoding='UTF-8'?>
<lsdb id='submission0001' xmlns='http://gen2phen.org/lsdb/2.0'
  xmlns:xsi='http://www.w3.org/2001/XMLSchema-instance' 
  xsi:schemaLocation='http://gen2phen.org/lsdb/1.1 
  file:/Users/muilu/Documents/Dev/SVN_repos/gen2phen/trunk/data_formats/xml/lsdb.xsd'>
 <source id='CD3Gbase' version='1.01' uri='http://bioinf.uta.fi/CD3Gbase/'>
	<name>CD3Gbase</name>
	<url>http://bioinf.uta.fi/CD3Gbase/</url>
	<contact>
		<name>Mauno Vihinen</name>
		<address>Institute of Medical Technology ,FI-33014 University of Tampere, Finland</address>
	</contact>
	<acknowledgement><name>Tampere University Hospital Medical Research Fund</name></acknowledgement>
	<acknowledgement><name>European Union</name></acknowledgement>
 </source>
</lsdb>
